{
  "project_info": {
    "project_number": "94740855187",
    "project_id": "light-micro-finance",
    "storage_bucket": "light-micro-finance.appspot.com"
  },
  "client": [
    {
      "client_info": {
        "mobilesdk_app_id": "1:94740855187:android:7aa82793a9c3e3b9e3d066",
        "android_client_info": {
          "package_name": "com.lightmicrofinance.app"
        }
      },
      "oauth_client": [
        {
          "client_id": "94740855187-qjic5hf52d6fgfk21urt32o6sl28qahq.apps.googleusercontent.com",
          "client_type": 3
        }
      ],
      "api_key": [
        {
          "current_key": "AIzaSyCP4-MjR6iJPI0Cm4851xdc2nUXxWQtqLo"
        }
      ],
      "services": {
        "appinvite_service": {
          "other_platform_oauth_client": [
            {
              "client_id": "94740855187-qjic5hf52d6fgfk21urt32o6sl28qahq.apps.googleusercontent.com",
              "client_type": 3
            }
          ]
        }
      }
    }
  ],
  "configuration_version": "1"
}